castleinyourmum
