Metadata-Version: 2.1
Name: castleinyourmum
Version: 1.0.3
Summary: A system
Home-page: UNKNOWN
Author: Xtev
License: UNKNOWN
Platform: UNKNOWN
